testio_mcp/__init__.py
testio_mcp/__main__.py
testio_mcp/api.py
testio_mcp/client.py
testio_mcp/config.py
testio_mcp/exceptions.py
testio_mcp/server.py
testio_mcp/validators.py
testio_mcp/cli/__init__.py
testio_mcp/cli/main.py
testio_mcp/cli/problematic.py
testio_mcp/cli/setup.py
testio_mcp/cli/sync.py
testio_mcp/database/__init__.py
testio_mcp/database/cache.py
testio_mcp/database/engine.py
testio_mcp/database/utils.py
testio_mcp/docs/__init__.py
testio_mcp/middleware/__init__.py
testio_mcp/middleware/error_handler.py
testio_mcp/models/__init__.py
testio_mcp/models/analytics.py
testio_mcp/models/orm/__init__.py
testio_mcp/models/orm/bug.py
testio_mcp/models/orm/feature.py
testio_mcp/models/orm/product.py
testio_mcp/models/orm/sync_event.py
testio_mcp/models/orm/sync_metadata.py
testio_mcp/models/orm/test.py
testio_mcp/models/orm/test_feature.py
testio_mcp/models/orm/test_platform.py
testio_mcp/models/orm/user.py
testio_mcp/prompts/__init__.py
testio_mcp/prompts/analyze_product_quality.md
testio_mcp/prompts/analyze_product_quality.py
testio_mcp/prompts/prep_meeting.md
testio_mcp/prompts/prep_meeting.py
testio_mcp/repositories/__init__.py
testio_mcp/repositories/base_repository.py
testio_mcp/repositories/bug_repository.py
testio_mcp/repositories/feature_repository.py
testio_mcp/repositories/fts5_query_builder.py
testio_mcp/repositories/product_repository.py
testio_mcp/repositories/search_repository.py
testio_mcp/repositories/test_repository.py
testio_mcp/repositories/user_repository.py
testio_mcp/resources/__init__.py
testio_mcp/resources/playbook.md
testio_mcp/resources/programmatic_access.md
testio_mcp/schemas/__init__.py
testio_mcp/schemas/constants.py
testio_mcp/schemas/dtos.py
testio_mcp/schemas/playbook_thresholds.py
testio_mcp/schemas/sync.py
testio_mcp/schemas/visualization_constants.py
testio_mcp/schemas/api/__init__.py
testio_mcp/schemas/api/bugs.py
testio_mcp/schemas/api/features.py
testio_mcp/schemas/api/products.py
testio_mcp/schemas/api/shared.py
testio_mcp-0.4.0.dist-info/METADATA
testio_mcp-0.4.0.dist-info/WHEEL
testio_mcp-0.4.0.dist-info/entry_points.txt
testio_mcp-0.4.0.dist-info/licenses/LICENSE
testio_mcp-0.4.0.dist-info/RECORD
