Metadata-Version: 2.4
Name: testio-mcp
Version: 0.4.0
Summary: Model Context Protocol server for TestIO Customer API integration
Project-URL: Homepage, https://github.com/test-IO/customer-mcp
Project-URL: Documentation, https://github.com/test-IO/customer-mcp#readme
Project-URL: Repository, https://github.com/test-IO/customer-mcp
Project-URL: Issues, https://github.com/test-IO/customer-mcp/issues
Author: TestIO MCP Team
License-Expression: LicenseRef-Proprietary
License-File: LICENSE
Keywords: ai,api,llm,mcp,model-context-protocol,testio
Classifier: Development Status :: 4 - Beta
Classifier: Intended Audience :: Developers
Classifier: Programming Language :: Python :: 3
Classifier: Programming Language :: Python :: 3.12
Classifier: Programming Language :: Python :: 3.13
Classifier: Topic :: Scientific/Engineering :: Artificial Intelligence
Classifier: Topic :: Software Development :: Libraries :: Python Modules
Requires-Python: >=3.12
Requires-Dist: aiosqlite>=0.20.0
Requires-Dist: alembic>=1.13.0
Requires-Dist: dateparser>=1.2.0
Requires-Dist: fastapi>=0.109.0
Requires-Dist: fastmcp>=2.12.0
Requires-Dist: filelock>=3.20.1
Requires-Dist: greenlet>=3.0.0
Requires-Dist: httpx>=0.28.0
Requires-Dist: psutil>=5.9.0
Requires-Dist: pydantic-settings>=2.11.0
Requires-Dist: pydantic>=2.12.0
Requires-Dist: python-dateutil>=2.8.0
Requires-Dist: python-dotenv>=1.0.0
Requires-Dist: rich>=13.7.0
Requires-Dist: sqlmodel>=0.0.16
Requires-Dist: tqdm>=4.66.0
Requires-Dist: urllib3>=2.6.0
Requires-Dist: uvicorn[standard]>=0.27.0
Provides-Extra: dev
Requires-Dist: bump-my-version>=0.28.0; extra == 'dev'
Requires-Dist: detect-secrets; extra == 'dev'
Requires-Dist: freezegun>=1.5.0; extra == 'dev'
Requires-Dist: mypy>=1.13.0; extra == 'dev'
Requires-Dist: pip-audit>=2.8.0; extra == 'dev'
Requires-Dist: pre-commit>=4.0.0; extra == 'dev'
Requires-Dist: pytest-alembic>=0.11.0; extra == 'dev'
Requires-Dist: pytest-asyncio>=0.24.0; extra == 'dev'
Requires-Dist: pytest-cov>=7.0.0; extra == 'dev'
Requires-Dist: pytest-httpx>=0.30.0; extra == 'dev'
Requires-Dist: pytest>=8.4.0; extra == 'dev'
Requires-Dist: ruff>=0.8.4; extra == 'dev'
Requires-Dist: types-dateparser>=1.2.0; extra == 'dev'
Requires-Dist: types-psutil>=5.9.0; extra == 'dev'
Requires-Dist: types-python-dateutil>=2.8.0; extra == 'dev'
